[
    {
        "Arquivo": "supply_chain_data_mao.csv",
        "Descrição": "Processos de produção e entrega de um produtos",
        "Formato": "csv",
        "Delimitador": ",",
        "Codificação": "UTF-8",
        "Número de linhas": 370,
        "Decimal": ",",
        "Colunas": [
            {
                "nome": " YEAR_MONTH",
                "tipo": "object",
                "descrição": "Ano e mês"
            },
            {
                "nome": "SKU",
                "tipo": "object",
                "descrição": "Stock Keeping Unit"
            },
            {
                "nome": " DESCRIPTION",
                "tipo": "object",
                "descrição": "Descrição do produto"
            },
            {
                "nome": " LEAD_TIMES",
                "tipo": "int64",
                "descrição": "Tempo de processo"
            },
            {
                "nome": " MANUFACTURING_COSTS",
                "tipo": "int64",
                "descrição": "Preço de produção"
            },
            {
                "nome": " CUSTOMER_NAME",
                "tipo": "object",
                "descrição": "Nome do comprador"
            },
            {
                "nome": " CUSTOMER_CITY",
                "tipo": "object",
                "descrição": "Cidade do comprador"
            },
            {
                "nome": " CUSTOMER_COUNTRY",
                "tipo": "object",
                "descrição": "País do comprador"
            },
            {
                "nome": " VIA_TRANSP",
                "tipo": "object",
                "descrição": "Modo de transporte"
            },
            {
                "nome": " SOLD_QUANTITY",
                "tipo": "int64",
                "descrição": "Quantidade vendida"
            },
            {
                "nome": "SOLD_PRICE",
                "tipo": "float64",
                "descrição": "Preço de venda"
            },
            {
                "nome": " FEIHT_ITEM",
                "tipo": "float64",
                "descrição": "Item fretado"
            }
        ],
        "Fonte": "Desconhecida",
        "Data da coleta": "2025-06-18",
        "Responsáveis": "Alexandra Amaro, Carlos Mota, Edney Farias, Maria Juliana Monte, Sidney Melo"
    }
]